python_opencv_toasty_animation/__init__.py
python_opencv_toasty_animation/animation.py
python_opencv_toasty_animation/toasty.py
python_opencv_toasty_animation-0.0.1.dist-info/LICENSE
python_opencv_toasty_animation-0.0.1.dist-info/METADATA
python_opencv_toasty_animation-0.0.1.dist-info/WHEEL
python_opencv_toasty_animation-0.0.1.dist-info/top_level.txt
python_opencv_toasty_animation-0.0.1.dist-info/RECORD
