Metadata-Version: 2.1
Name: python_opencv_toasty_animation
Version: 0.0.1
Summary: Toasty animation to play in top of OpenCV VideoCapture
Author-email: Yamil Jaskolowski <yamilj@gmail.com>
Project-URL: Homepage, https://github.com/adremides/python_opencv_toasty_animation
Project-URL: Issues, https://github.com/pypa/python_opencv_toasty_animation/issues
Classifier: Programming Language :: Python :: 3
Classifier: License :: OSI Approved :: GNU General Public License v3 or later (GPLv3+)
Classifier: Operating System :: OS Independent
Requires-Python: >=3.10
License-File: LICENSE
